sumtypes.py
sumtypes-0.1a6.dist-info/LICENSE
sumtypes-0.1a6.dist-info/METADATA
sumtypes-0.1a6.dist-info/WHEEL
sumtypes-0.1a6.dist-info/top_level.txt
sumtypes-0.1a6.dist-info/RECORD
