Metadata-Version: 1.1
Name: sumtypes
Version: 0.1a6
Summary: Algebraic types for Python (notably providing Sum Types, aka Tagged Unions)
Home-page: http://github.com/radix/sumtypes/
Author: Christopher Armstrong
Author-email: UNKNOWN
License: MIT
Platform: UNKNOWN
Classifier: License :: OSI Approved :: MIT License
Classifier: Programming Language :: Python :: 2
Classifier: Programming Language :: Python :: 3
